{
  "_name": "minecraft:emerald_ore",
  "stats": {
    "opacity": 255,
    "brightness": 0,
    "hardness": 3.0,
    "resistance": 15.0,
    "sound": "piston",
    "slipperiness": 0.6,
    "tool_data": [
      {
        "tool": "pickaxe",
        "level": 2
      }
    ]
  },
  "break_speed": [],
  "drops": [
    {
        "function": "default",
        "value": false
    },
    {
        "function": "add",
        "id": "minecraft:emerald_ore"
    },
    {
        "function": "remove",
        "id": "minecraft:emerald"
    }
        ],
  "harvest": [],
  "xp": [
    {   "function": "set",
        "value": 0
    }
        ]
}